setup.py
LinearRegressionBasic/LinearRegression.py
LinearRegressionBasic/SingleVariableLinearRegression.py
LinearRegressionBasic/__init__.py
LinearRegressionBasic.egg-info/PKG-INFO
LinearRegressionBasic.egg-info/SOURCES.txt
LinearRegressionBasic.egg-info/dependency_links.txt
LinearRegressionBasic.egg-info/not-zip-safe
LinearRegressionBasic.egg-info/top_level.txt