Metadata-Version: 1.0
Name: LinearRegressionBasic
Version: 1.2
Summary: Linear Regression X,Y Values Calculation
Home-page: UNKNOWN
Author: Iris Zhao
Author-email: izhao1993@gmail.com
License: UNKNOWN
Platform: UNKNOWN
